LICENSE
MANIFEST.in
README.md
pyproject.toml
requirements.txt
setup.py
mars_agent/__init__.py
mars_agent/schema.py
mars_agent.egg-info/PKG-INFO
mars_agent.egg-info/SOURCES.txt
mars_agent.egg-info/dependency_links.txt
mars_agent.egg-info/not-zip-safe
mars_agent.egg-info/requires.txt
mars_agent.egg-info/top_level.txt
mars_agent/agents/__init__.py
mars_agent/agents/mars_agent.py
mars_agent/agents/mcp_agent.py
mars_agent/agents/plan_agent.py
mars_agent/agents/stream_agent.py
mars_agent/core/__init__.py
mars_agent/core/mcp/__init__.py
mars_agent/core/mcp/manager.py
mars_agent/core/mcp/multi_client.py
mars_agent/core/mcp/schema.py
mars_agent/core/mcp/sessions.py
mars_agent/core/mcp/load_mcp/__init__.py
mars_agent/core/mcp/load_mcp/prompts.py
mars_agent/core/mcp/load_mcp/resources.py
mars_agent/core/mcp/load_mcp/tools.py
mars_agent/core/models/__init__.py
mars_agent/core/models/base_model.py
mars_agent/core/models/conversation_model.py
mars_agent/core/models/manager.py
mars_agent/core/models/reason_model.py
mars_agent/core/models/tool_call_model.py
mars_agent/prompts/chat_prompt.py
mars_agent/utils/__init__.py
mars_agent/utils/event_manager.py
mars_agent/utils/util.py