Metadata-Version: 2.4
Name: mars-agent
Version: 0.1.1
Summary: Mars Agent - 基于主副代理架构的AI代理系统，支持MCP协议和流式处理
Home-page: https://github.com/Shy2593666979/Mars-Agent
Author: MingGuang Tian
Author-email: MingGuang Tian <2593666979@qq.com>
License: Apache-2.0
Project-URL: Homepage, https://github.com/Shy2593666979/Mars-Agent
Project-URL: Repository, https://github.com/Shy2593666979/Mars-Agent
Project-URL: Documentation, https://github.com/Shy2593666979/Mars-Agent#readme
Project-URL: Bug Tracker, https://github.com/Shy2593666979/Mars-Agent/issues
Keywords: ai,agent,mcp,streaming,llm,chatbot
Classifier: Development Status :: 3 - Alpha
Classifier: Intended Audience :: Developers
Classifier: License :: OSI Approved :: Apache Software License
Classifier: Operating System :: OS Independent
Classifier: Programming Language :: Python :: 3
Classifier: Programming Language :: Python :: 3.11
Classifier: Programming Language :: Python :: 3.12
Classifier: Topic :: Software Development :: Libraries :: Python Modules
Classifier: Topic :: Scientific/Engineering :: Artificial Intelligence
Requires-Python: >=3.11
License-File: LICENSE
Requires-Dist: mcp>=1.8.0
Requires-Dist: openai>=1.12.0
Requires-Dist: langgraph>=0.3.0
Provides-Extra: dev
Requires-Dist: pytest>=7.0; extra == "dev"
Requires-Dist: pytest-asyncio>=0.21.0; extra == "dev"
Requires-Dist: black>=23.0; extra == "dev"
Requires-Dist: flake8>=6.0; extra == "dev"
Requires-Dist: mypy>=1.0; extra == "dev"
Dynamic: author
Dynamic: home-page
Dynamic: license-file
Dynamic: requires-python
